pretty_poly/__init__.py
pretty_poly/abstract.py
pretty_poly/ascii.py
pretty_poly/display_result.py
pretty_poly/image.py
pretty_poly/png.py
pretty_poly/svg.py
pretty_poly/tiling.py
pretty_poly-0.5.0.dist-info/entry_points.txt
pretty_poly-0.5.0.dist-info/LICENSE
pretty_poly-0.5.0.dist-info/WHEEL
pretty_poly-0.5.0.dist-info/METADATA
pretty_poly-0.5.0.dist-info/RECORD
