Metadata-Version: 2.1
Name: pretty-poly
Version: 0.5.0
Summary: Display polyominos and polyomino tilings in various pretty formats.
Home-page: https://github.com/jwg4/pretty_poly
License: MIT
Author: Jack Grahl
Author-email: jack.grahl@gmail.com
Requires-Python: >=3.7,<4.0
Classifier: License :: OSI Approved :: MIT License
Classifier: Programming Language :: Python :: 3
Classifier: Programming Language :: Python :: 3.10
Classifier: Programming Language :: Python :: 3.7
Classifier: Programming Language :: Python :: 3.8
Classifier: Programming Language :: Python :: 3.9
Requires-Dist: pypng (>=0.0.20,<0.0.21)
Requires-Dist: svgwrite (>=1.4.1,<2.0.0)
Project-URL: Repository, https://github.com/jwg4/pretty_poly.git
